[
  { "id": "1", "name": "city name", "link": "page1" },
  { "id": "1", "name": "city name", "link": "page1" },
  { "id": "1", "name": "city name", "link": "page1" },
  { "id": "1", "name": "city name", "link": "page1" },
  { "id": "1", "name": "city name", "link": "page1" },
  { "id": "1", "name": "city name", "link": "page1" },
  { "id": "1", "name": "city name", "link": "page1" },
  { "id": "1", "name": "city name", "link": "page1" },
  { "id": "1", "name": "city name", "link": "page1" },
  { "id": "1", "name": "city name", "link": "page1" },
  { "id": "1", "name": "city name", "link": "page1" },
  { "id": "1", "name": "city name", "link": "page1" }
]
